<?xml version='1.0' encoding='UTF-8'?>
<Document docname="94"><Content><ID>94</ID><Titulo>Receita de Falso chantily</Titulo><Receita><TempoPreparo>5min</TempoPreparo><QuantidadePorcoes>8 portions</QuantidadePorcoes><Votos>50 votos</Votos><Conteudo>&lt;ul&gt;&lt;li&gt;&lt;span&gt;1 copo de requeijão de leite&lt;/span&gt;&lt;/li&gt;&lt;li&gt;&lt;span&gt;1 copo de requijão de açúcar&lt;/span&gt;&lt;/li&gt;&lt;li&gt;&lt;span&gt;1 colher de sopa (cheia) de emulsificante para sorvete (emustab)&lt;/span&gt;&lt;/li&gt;&lt;li&gt;&lt;span&gt;1 colher de sopa cheia de gelatina de qualquer sabor (ou sem sabor)&lt;/span&gt;&lt;/li&gt;&lt;/ul&gt;
&lt;ol&gt;&lt;li class="odd"&gt;&lt;span&gt;Coloque tudo numa vasilha e bata até dar ponto de chantily&lt;/span&gt;&lt;/li&gt;&lt;li&gt;&lt;span&gt;A gelatina sem sabor dissolver conforme embalagem, já com sabor é bom dissolver c/ 2 colheres de água quente&lt;/span&gt;&lt;/li&gt;&lt;li class="odd"&gt;&lt;span&gt;Pode fazer sem a gelatina se for usar em saladas de frutas, com morangos, sorvetes, pavês, etc&lt;/span&gt;&lt;/li&gt;&lt;li&gt;&lt;span&gt;Nesse caso pingue umas gotinhas de essência de baunilha branca ou de sua preferência na hora de bater&lt;/span&gt;&lt;/li&gt;&lt;li class="odd"&gt;&lt;span&gt;A gelatina serve para dar firmeza no caso de confeitar bolos, para não desmanchar&lt;/span&gt;&lt;/li&gt;&lt;li&gt;&lt;span&gt;&lt;em&gt;Obs:&lt;/em&gt; Fica muito leve, é econômica, gostosa e não é gordurosa como os chantily comuns&lt;/span&gt;&lt;/li&gt;&lt;li class="odd"&gt;&lt;span&gt;Rende um pote de sorvete de 2 litros&lt;/span&gt;&lt;/li&gt;&lt;/ol&gt;&lt;strong class="session"&gt;Dicas:&lt;/strong&gt;&lt;ol&gt;&lt;li class="odd"&gt;&lt;span&gt;Não congelar, conservar em geladeira&lt;/span&gt;&lt;/li&gt;&lt;/ol&gt;
</Conteudo></Receita></Content></Document>