<?xml version='1.0' encoding='UTF-8'?>
<Document docname="78"><Content><ID>78</ID><Titulo>Receita de Po de mel</Titulo><Receita><TempoPreparo>50min</TempoPreparo><QuantidadePorcoes>0 portions</QuantidadePorcoes><Votos>43 votos</Votos><Conteudo>&lt;ul&gt;&lt;li&gt;&lt;span&gt;1 lata de leite condensado&lt;/span&gt;&lt;/li&gt;&lt;li&gt;&lt;span&gt;400 ml de leite&lt;/span&gt;&lt;/li&gt;&lt;li&gt;&lt;span&gt;½ xícara (chá) de mel&lt;/span&gt;&lt;/li&gt;&lt;li&gt;&lt;span&gt;3 colheres (sopa) de canela em pó&lt;/span&gt;&lt;/li&gt;&lt;li&gt;&lt;span&gt;1 colher (sopa) de cravo em pó&lt;/span&gt;&lt;/li&gt;&lt;li&gt;&lt;span&gt;1 colher (sopa rasa) de bicarbonato de sódio&lt;/span&gt;&lt;/li&gt;&lt;li&gt;&lt;span&gt;3 xícaras (chá) de farinha de trigo (330 g)&lt;/span&gt;&lt;/li&gt;&lt;li&gt;&lt;span&gt;1 colher (sopa) de fermento em pó&lt;/span&gt;&lt;/li&gt;&lt;/ul&gt;&lt;strong class="session"&gt;Sugestão de recheio:&lt;/strong&gt;&lt;ul&gt;&lt;li&gt;&lt;span&gt;1 lata de leite condensado cozido por 1 hora na pressão&lt;/span&gt;&lt;/li&gt;&lt;li&gt;&lt;span&gt;1 lata de creme de leite sem soro&lt;/span&gt;&lt;/li&gt;&lt;li&gt;&lt;span&gt;4 colheres (sopa-cheia) de chocolate em pó&lt;/span&gt;&lt;/li&gt;&lt;/ul&gt;&lt;strong class="session"&gt;Para a cobertura:&lt;/strong&gt;&lt;ul&gt;&lt;li&gt;&lt;span&gt;500 g de chocolate ao leite para cobertura picado&lt;/span&gt;&lt;/li&gt;&lt;li&gt;&lt;span&gt;300 g de chocolate meio amargo picado&lt;/span&gt;&lt;/li&gt;&lt;li&gt;&lt;span&gt;1 colher (sopa) gordura vegetal hidrogenada&lt;/span&gt;&lt;/li&gt;&lt;/ul&gt;
&lt;ol&gt;&lt;li class="odd"&gt;&lt;span&gt;No liquidificador, bata os 3 primeiros ingredientes&lt;/span&gt;&lt;/li&gt;&lt;li&gt;&lt;span&gt;Coloque numa vasilha e misture os outros ingredientes peneirados&lt;/span&gt;&lt;/li&gt;&lt;li class="odd"&gt;&lt;span&gt;Despeje numa forma untada e enfarinhada (25x35 cm), espalhe a massa e asse em forno pré-aquecido a 180ºC por cerca de 20 minutos&lt;/span&gt;&lt;/li&gt;&lt;li&gt;&lt;span&gt;Corte no formato desejado e recheie&lt;/span&gt;&lt;/li&gt;&lt;/ol&gt;&lt;strong class="session"&gt;Sugestão de recheio:&lt;/strong&gt;&lt;ol&gt;&lt;li class="odd"&gt;&lt;span&gt;Misture os ingredientes e leve à geladeira para encorpar por mais ou menos 2 horas&lt;/span&gt;&lt;/li&gt;&lt;li&gt;&lt;span&gt;Recheie os pães de mel e passe uma fina camada nas laterais e na parte de cima antes de banhar com a cobertura&lt;/span&gt;&lt;/li&gt;&lt;/ol&gt;&lt;strong class="session"&gt;Para a cobertura:&lt;/strong&gt;&lt;ol&gt;&lt;li class="odd"&gt;&lt;span&gt;Derreta os ingredientes em banho-maria e passe os pães de mel&lt;/span&gt;&lt;/li&gt;&lt;li&gt;&lt;span&gt;Coloque-os sobre uma grade para escorrer&lt;/span&gt;&lt;/li&gt;&lt;/ol&gt;
</Conteudo></Receita></Content></Document>